{
  "method": "ivfpq",
  "param_name": "nprobe",
  "target_recall": 0.9,
  "target_reached": false,
  "calibrated_param_value": 256,
  "achieved_recall_vs_exact": 0.88383,
  "latency_ms_at_calibrated": {
    "mean": 0.3470722000201931,
    "p50": 0.3446500004429254,
    "p95": 0.3691450001497287
  },
  "topk": 100,
  "n_calibration_queries": 1000,
  "seed": 42,
  "sweep": [
    {
      "param_value": 1,
      "recall_vs_exact": 0.4486,
      "latency_ms": {
        "mean": 0.052359000030264724,
        "p50": 0.05109999983687885,
        "p95": 0.06090499991842079
      }
    },
    {
      "param_value": 2,
      "recall_vs_exact": 0.62336,
      "latency_ms": {
        "mean": 0.03552560000389349,
        "p50": 0.03470000046945643,
        "p95": 0.04150499944444163
      }
    },
    {
      "param_value": 4,
      "recall_vs_exact": 0.76251,
      "latency_ms": {
        "mean": 0.042130600013479125,
        "p50": 0.0411000000895001,
        "p95": 0.053710001338913564
      }
    },
    {
      "param_value": 8,
      "recall_vs_exact": 0.83763,
      "latency_ms": {
        "mean": 0.05154220005351817,
        "p50": 0.05069999951956561,
        "p95": 0.06150500075818854
      }
    },
    {
      "param_value": 16,
      "recall_vs_exact": 0.86988,
      "latency_ms": {
        "mean": 0.06924940001408686,
        "p50": 0.06820000089646783,
        "p95": 0.08131500053423223
      }
    },
    {
      "param_value": 32,
      "recall_vs_exact": 0.88067,
      "latency_ms": {
        "mean": 0.1043453999736812,
        "p50": 0.10270000075252028,
        "p95": 0.12130499962950125
      }
    },
    {
      "param_value": 64,
      "recall_vs_exact": 0.88339,
      "latency_ms": {
        "mean": 0.1748747999808984,
        "p50": 0.17209999987244373,
        "p95": 0.20053000052939748
      }
    },
    {
      "param_value": 128,
      "recall_vs_exact": 0.88378,
      "latency_ms": {
        "mean": 0.3030603999795858,
        "p50": 0.2997999999934109,
        "p95": 0.3342099999827042
      }
    },
    {
      "param_value": 256,
      "recall_vs_exact": 0.88383,
      "latency_ms": {
        "mean": 0.3470722000201931,
        "p50": 0.3446500004429254,
        "p95": 0.3691450001497287
      }
    }
  ],
  "dataset": "ml-20m",
  "weighting": "bm25",
  "dim": 128
}